databridge/__init__.py
databridge/async_.py
databridge/exceptions.py
databridge/models.py
databridge/rules.py
databridge/sync.py
databridge_client-0.3.0.dist-info/METADATA
databridge_client-0.3.0.dist-info/WHEEL
databridge_client-0.3.0.dist-info/RECORD
