Metadata-Version: 2.4
Name: databridge-client
Version: 0.3.0
Summary: DataBridge Python Client
Author-email: DataBridge <databridgesuperuser@gmail.com>
Requires-Python: >=3.8
Requires-Dist: httpx>=0.24.0
Requires-Dist: pillow==10.4.0
Requires-Dist: pydantic==2.10.3
Requires-Dist: pyjwt>=2.0.0
Requires-Dist: requests>=2.32.3
